{
  "date": "2026-05-12",
  "build_time_utc": "2026-05-12 12:49 UTC",
  "mrmi": {
    "composite": 0.39877024614345524,
    "state": "green"
  },
  "components": {
    "gii_fast": 0.3219105077970716,
    "fincon": 0.28643930424983005,
    "breadth": 0.587960926383464
  },
  "mrci": {
    "composite": 0.7522172627158396,
    "real_economy": -0.07920188512533138,
    "credit_money": 0.016846257431404554,
    "markets": null,
    "labor": 1.5836364105570104
  },
  "inflation": 0.8031542384892865,
  "mrmi_combined": {
    "value": 0.8987702461434552,
    "state": "LONG",
    "momentum": 0.39877024614345524,
    "stress_intensity": 0.0,
    "macro_buffer": 1.0,
    "buffer_size": 1.0
  },
  "macro": {
    "real_economy_score": -0.8811316090618446,
    "real_economy_components": {
      "pce": -1.179200811744738,
      "labor_inv": 0.7217849701718074,
      "income": -3.7123333947461012,
      "gdpnow": 0.645222800071653
    },
    "inflation_dir_pp": -0.41779912039896505,
    "core_cpi_yoy_pct": 2.602167705486824,
    "raw": {
      "pce_yoy": 2.1237343140179776,
      "sahm_rule": 0.18222222222222229,
      "income_yoy": 0.23352655417341328,
      "gdpnow": 3.7469
    }
  },
  "underliers": {
    "^GSPC": 7412.83984375,
    "IWM": 285.3299865722656,
    "BTC-USD": 80947.203125,
    "^VIX": 18.780000686645508,
    "^MOVE": 70.73999786376953,
    "^TNX": 4.428999900817871,
    "HYG": 79.9800033569336,
    "HG=F": 6.483500003814697,
    "GC=F": 4709.5,
    "DBC": 31.059999465942383,
    "DGS10": 4.38,
    "DGS2": 3.9,
    "DGS3MO": 3.69,
    "DFII10": 1.93,
    "BAMLH0A0HYM2": 2.81,
    "T5YIE": 2.67,
    "T10YIE": 2.47,
    "ICSA": 200000.0,
    "CCSA": 1766000.0,
    "DTWEXBGS": 118.0392,
    "WALCL": 6709505.0,
    "WTREGEN": 877761.0,
    "RRPONTSYD": 1.133
  }
}